lotkavolterra_simulator/__init__.py
lotkavolterra_simulator/simulator.py
lotkavolterra_simulator-1.0.dist-info/LICENSE
lotkavolterra_simulator-1.0.dist-info/METADATA
lotkavolterra_simulator-1.0.dist-info/WHEEL
lotkavolterra_simulator-1.0.dist-info/top_level.txt
lotkavolterra_simulator-1.0.dist-info/RECORD
