Metadata-Version: 2.1
Name: lotkavolterra-simulator
Version: 1.0
Summary: Simulator of the Lotka-Volterra prey-predator system with demographic and observational noise and biases
Author-email: Florent Leclercq <florent.leclercq@polytechnique.org>
Project-URL: Homepage, https://github.com/florent-leclercq/lotkavolterra_simulator
Project-URL: Bug Tracker, https://github.com/florent-leclercq/lotkavolterra_simulator/issues
Classifier: Programming Language :: Python :: 3
Classifier: License :: OSI Approved :: GNU General Public License v3 or later (GPLv3+)
Classifier: Operating System :: OS Independent
Requires-Python: >=3.7
License-File: LICENSE
